{"epoch_idx": 0, "edge_path_idx": 0, "edge_chunk_idx": 0, "lhs_partition": 0, "rhs_partition": 0, "index": 1, "stats": {"count": 23707132, "metrics": {"loss": 10.103516185757215, "violators_lhs": 21.589572370036155, "violators_rhs": 21.963975566508847}}}
{"epoch_idx": 1, "edge_path_idx": 0, "edge_chunk_idx": 0, "lhs_partition": 0, "rhs_partition": 0, "index": 2, "stats": {"count": 23707132, "metrics": {"loss": 2.0262048077835058, "violators_lhs": 3.6926529535500117, "violators_rhs": 3.835001298343469}}}
{"epoch_idx": 2, "edge_path_idx": 0, "edge_chunk_idx": 0, "lhs_partition": 0, "rhs_partition": 0, "index": 3, "stats": {"count": 23707132, "metrics": {"loss": 1.5186223559155663, "violators_lhs": 2.681989158368039, "violators_rhs": 2.69734681529592}}}
{"epoch_idx": 3, "edge_path_idx": 0, "edge_chunk_idx": 0, "lhs_partition": 0, "rhs_partition": 0, "index": 4, "stats": {"count": 23707132, "metrics": {"loss": 1.31982280347961, "violators_lhs": 2.2929197002825985, "violators_rhs": 2.2807636537393052}}}
{"epoch_idx": 4, "edge_path_idx": 0, "edge_chunk_idx": 0, "lhs_partition": 0, "rhs_partition": 0, "index": 5, "stats": {"count": 23707132, "metrics": {"loss": 1.2034609099149303, "violators_lhs": 2.07105292196458, "violators_rhs": 2.0537616275136106}}}
{"epoch_idx": 5, "edge_path_idx": 0, "edge_chunk_idx": 0, "lhs_partition": 0, "rhs_partition": 0, "index": 6, "stats": {"count": 23707132, "metrics": {"loss": 1.1254448487361322, "violators_lhs": 1.9263584477447546, "violators_rhs": 1.9109211523350864}}}
{"epoch_idx": 6, "edge_path_idx": 0, "edge_chunk_idx": 0, "lhs_partition": 0, "rhs_partition": 0, "index": 7, "stats": {"count": 23707132, "metrics": {"loss": 1.0692424861804328, "violators_lhs": 1.8227682707465416, "violators_rhs": 1.8133876759111984}}}
{"epoch_idx": 7, "edge_path_idx": 0, "edge_chunk_idx": 0, "lhs_partition": 0, "rhs_partition": 0, "index": 8, "stats": {"count": 23707132, "metrics": {"loss": 1.0270101248679535, "violators_lhs": 1.74469252543918, "violators_rhs": 1.7430660950468408}}}
{"epoch_idx": 8, "edge_path_idx": 0, "edge_chunk_idx": 0, "lhs_partition": 0, "rhs_partition": 0, "index": 9, "stats": {"count": 23707132, "metrics": {"loss": 0.9941047634036608, "violators_lhs": 1.6833464714331536, "violators_rhs": 1.6902980925739983}}}
{"epoch_idx": 9, "edge_path_idx": 0, "edge_chunk_idx": 0, "lhs_partition": 0, "rhs_partition": 0, "index": 10, "stats": {"count": 23707132, "metrics": {"loss": 0.9676374670364888, "violators_lhs": 1.6324325101830115, "violators_rhs": 1.6486558981491308}}}
{"epoch_idx": 10, "edge_path_idx": 0, "edge_chunk_idx": 0, "lhs_partition": 0, "rhs_partition": 0, "index": 11, "stats": {"count": 23707132, "metrics": {"loss": 0.9460479921834628, "violators_lhs": 1.5900558110529777, "violators_rhs": 1.6166103095051734}}}
{"epoch_idx": 11, "edge_path_idx": 0, "edge_chunk_idx": 0, "lhs_partition": 0, "rhs_partition": 0, "index": 12, "stats": {"count": 23707132, "metrics": {"loss": 0.928100714337947, "violators_lhs": 1.5541484309447469, "violators_rhs": 1.5902921534329837}}}
{"epoch_idx": 12, "edge_path_idx": 0, "edge_chunk_idx": 0, "lhs_partition": 0, "rhs_partition": 0, "index": 13, "stats": {"count": 23707132, "metrics": {"loss": 0.912796203468087, "violators_lhs": 1.5222541047985054, "violators_rhs": 1.5677693531212464}}}
{"epoch_idx": 13, "edge_path_idx": 0, "edge_chunk_idx": 0, "lhs_partition": 0, "rhs_partition": 0, "index": 14, "stats": {"count": 23707132, "metrics": {"loss": 0.8998493572187145, "violators_lhs": 1.495206210519265, "violators_rhs": 1.5496806614988266}}}
{"epoch_idx": 14, "edge_path_idx": 0, "edge_chunk_idx": 0, "lhs_partition": 0, "rhs_partition": 0, "index": 15, "stats": {"count": 23707132, "metrics": {"loss": 0.8883420919307365, "violators_lhs": 1.4705627825415575, "violators_rhs": 1.5337961167128946}}}
{"epoch_idx": 15, "edge_path_idx": 0, "edge_chunk_idx": 0, "lhs_partition": 0, "rhs_partition": 0, "index": 16, "stats": {"count": 23707132, "metrics": {"loss": 0.8785707886460445, "violators_lhs": 1.4495970664017899, "violators_rhs": 1.520766535572502}}}
{"epoch_idx": 16, "edge_path_idx": 0, "edge_chunk_idx": 0, "lhs_partition": 0, "rhs_partition": 0, "index": 17, "stats": {"count": 23707132, "metrics": {"loss": 0.8696214727773066, "violators_lhs": 1.4297979612211211, "violators_rhs": 1.5086534296936467}}}
{"epoch_idx": 17, "edge_path_idx": 0, "edge_chunk_idx": 0, "lhs_partition": 0, "rhs_partition": 0, "index": 18, "stats": {"count": 23707132, "metrics": {"loss": 0.8617384841037062, "violators_lhs": 1.412198784737015, "violators_rhs": 1.4986566489780375}}}
{"epoch_idx": 18, "edge_path_idx": 0, "edge_chunk_idx": 0, "lhs_partition": 0, "rhs_partition": 0, "index": 19, "stats": {"count": 23707132, "metrics": {"loss": 0.8546424123414732, "violators_lhs": 1.3969623571505823, "violators_rhs": 1.4895651232717648}}}
{"epoch_idx": 19, "edge_path_idx": 0, "edge_chunk_idx": 0, "lhs_partition": 0, "rhs_partition": 0, "index": 20, "stats": {"count": 23707132, "metrics": {"loss": 0.8482732099001887, "violators_lhs": 1.382647930588989, "violators_rhs": 1.4811020582329402}}}
{"epoch_idx": 20, "edge_path_idx": 0, "edge_chunk_idx": 0, "lhs_partition": 0, "rhs_partition": 0, "index": 21, "stats": {"count": 23707132, "metrics": {"loss": 0.8424729912746719, "violators_lhs": 1.3703027004700525, "violators_rhs": 1.473942398430987}}}
{"epoch_idx": 21, "edge_path_idx": 0, "edge_chunk_idx": 0, "lhs_partition": 0, "rhs_partition": 0, "index": 22, "stats": {"count": 23707132, "metrics": {"loss": 0.8371457079719311, "violators_lhs": 1.3584901370608642, "violators_rhs": 1.4673257397815982}}}
{"epoch_idx": 22, "edge_path_idx": 0, "edge_chunk_idx": 0, "lhs_partition": 0, "rhs_partition": 0, "index": 23, "stats": {"count": 23707132, "metrics": {"loss": 0.8320453782907465, "violators_lhs": 1.347357875258804, "violators_rhs": 1.4607696114401354}}}
{"epoch_idx": 23, "edge_path_idx": 0, "edge_chunk_idx": 0, "lhs_partition": 0, "rhs_partition": 0, "index": 24, "stats": {"count": 23707132, "metrics": {"loss": 0.8277901884826303, "violators_lhs": 1.3374807631728713, "violators_rhs": 1.4564393111743756}}}
{"epoch_idx": 24, "edge_path_idx": 0, "edge_chunk_idx": 0, "lhs_partition": 0, "rhs_partition": 0, "index": 25, "stats": {"count": 23707132, "metrics": {"loss": 0.8234816025544788, "violators_lhs": 1.3283754019676441, "violators_rhs": 1.4506857683164711}}}
{"epoch_idx": 25, "edge_path_idx": 0, "edge_chunk_idx": 0, "lhs_partition": 0, "rhs_partition": 0, "index": 26, "stats": {"count": 23707132, "metrics": {"loss": 0.8196915818013218, "violators_lhs": 1.3197957897226877, "violators_rhs": 1.4467523106548696}}}
{"epoch_idx": 26, "edge_path_idx": 0, "edge_chunk_idx": 0, "lhs_partition": 0, "rhs_partition": 0, "index": 27, "stats": {"count": 23707132, "metrics": {"loss": 0.8159855882028068, "violators_lhs": 1.3122392873165762, "violators_rhs": 1.4422000518662486}}}
{"epoch_idx": 27, "edge_path_idx": 0, "edge_chunk_idx": 0, "lhs_partition": 0, "rhs_partition": 0, "index": 28, "stats": {"count": 23707132, "metrics": {"loss": 0.8126075131341896, "violators_lhs": 1.3047100340943814, "violators_rhs": 1.4380042259013026}}}
{"epoch_idx": 28, "edge_path_idx": 0, "edge_chunk_idx": 0, "lhs_partition": 0, "rhs_partition": 0, "index": 29, "stats": {"count": 23707132, "metrics": {"loss": 0.8094611045123484, "violators_lhs": 1.2978763943272429, "violators_rhs": 1.4344690450114337}}}
{"epoch_idx": 29, "edge_path_idx": 0, "edge_chunk_idx": 0, "lhs_partition": 0, "rhs_partition": 0, "index": 30, "stats": {"count": 23707132, "metrics": {"loss": 0.8066273071217037, "violators_lhs": 1.2919207182041252, "violators_rhs": 1.4317957566524706}}}
{"epoch_idx": 30, "edge_path_idx": 0, "edge_chunk_idx": 0, "lhs_partition": 0, "rhs_partition": 0, "index": 31, "stats": {"count": 23707132, "metrics": {"loss": 0.8037499562108469, "violators_lhs": 1.2856474161446438, "violators_rhs": 1.4282186052703465}}}
{"epoch_idx": 31, "edge_path_idx": 0, "edge_chunk_idx": 0, "lhs_partition": 0, "rhs_partition": 0, "index": 32, "stats": {"count": 23707132, "metrics": {"loss": 0.8010363791369598, "violators_lhs": 1.2799174105075215, "violators_rhs": 1.4253375313386705}}}
{"epoch_idx": 32, "edge_path_idx": 0, "edge_chunk_idx": 0, "lhs_partition": 0, "rhs_partition": 0, "index": 33, "stats": {"count": 23707132, "metrics": {"loss": 0.7986934359689858, "violators_lhs": 1.274708809146547, "violators_rhs": 1.4224369274191413}}}
{"epoch_idx": 33, "edge_path_idx": 0, "edge_chunk_idx": 0, "lhs_partition": 0, "rhs_partition": 0, "index": 34, "stats": {"count": 23707132, "metrics": {"loss": 0.7962644498497173, "violators_lhs": 1.270015495758829, "violators_rhs": 1.419991376434737}}}
{"epoch_idx": 34, "edge_path_idx": 0, "edge_chunk_idx": 0, "lhs_partition": 0, "rhs_partition": 0, "index": 35, "stats": {"count": 23707132, "metrics": {"loss": 0.7939979027619611, "violators_lhs": 1.2646973071225993, "violators_rhs": 1.4175632463682237}}}
{"epoch_idx": 35, "edge_path_idx": 0, "edge_chunk_idx": 0, "lhs_partition": 0, "rhs_partition": 0, "index": 36, "stats": {"count": 23707132, "metrics": {"loss": 0.7919757344552203, "violators_lhs": 1.2601567325815708, "violators_rhs": 1.4156088977781032}}}
{"epoch_idx": 36, "edge_path_idx": 0, "edge_chunk_idx": 0, "lhs_partition": 0, "rhs_partition": 0, "index": 37, "stats": {"count": 23707132, "metrics": {"loss": 0.7898223548559192, "violators_lhs": 1.2558617803283838, "violators_rhs": 1.4130165555243037}}}
{"epoch_idx": 37, "edge_path_idx": 0, "edge_chunk_idx": 0, "lhs_partition": 0, "rhs_partition": 0, "index": 38, "stats": {"count": 23707132, "metrics": {"loss": 0.788012190532144, "violators_lhs": 1.2521151862654665, "violators_rhs": 1.4114482932815324}}}
{"epoch_idx": 38, "edge_path_idx": 0, "edge_chunk_idx": 0, "lhs_partition": 0, "rhs_partition": 0, "index": 39, "stats": {"count": 23707132, "metrics": {"loss": 0.7861386742289815, "violators_lhs": 1.2478757447336946, "violators_rhs": 1.4093735167965489}}}
{"epoch_idx": 39, "edge_path_idx": 0, "edge_chunk_idx": 0, "lhs_partition": 0, "rhs_partition": 0, "index": 40, "stats": {"count": 23707132, "metrics": {"loss": 0.7843417221806808, "violators_lhs": 1.2443904222577409, "violators_rhs": 1.4072499364326314}}}
{"epoch_idx": 40, "edge_path_idx": 0, "edge_chunk_idx": 0, "lhs_partition": 0, "rhs_partition": 0, "index": 41, "stats": {"count": 23707132, "metrics": {"loss": 0.7827112374205824, "violators_lhs": 1.240941628873539, "violators_rhs": 1.4057881822229699}}}
{"epoch_idx": 41, "edge_path_idx": 0, "edge_chunk_idx": 0, "lhs_partition": 0, "rhs_partition": 0, "index": 42, "stats": {"count": 23707132, "metrics": {"loss": 0.781053139596348, "violators_lhs": 1.2376613079979477, "violators_rhs": 1.4035420648942267}}}
{"epoch_idx": 42, "edge_path_idx": 0, "edge_chunk_idx": 0, "lhs_partition": 0, "rhs_partition": 0, "index": 43, "stats": {"count": 23707132, "metrics": {"loss": 0.7795673762331801, "violators_lhs": 1.2341480614356894, "violators_rhs": 1.4023458847742527}}}
{"epoch_idx": 43, "edge_path_idx": 0, "edge_chunk_idx": 0, "lhs_partition": 0, "rhs_partition": 0, "index": 44, "stats": {"count": 23707132, "metrics": {"loss": 0.777974526113202, "violators_lhs": 1.2310110307733555, "violators_rhs": 1.4004260405687199}}}
{"epoch_idx": 44, "edge_path_idx": 0, "edge_chunk_idx": 0, "lhs_partition": 0, "rhs_partition": 0, "index": 45, "stats": {"count": 23707132, "metrics": {"loss": 0.7766528019006419, "violators_lhs": 1.2279733373062587, "violators_rhs": 1.3991066485815324}}}
{"epoch_idx": 45, "edge_path_idx": 0, "edge_chunk_idx": 0, "lhs_partition": 0, "rhs_partition": 0, "index": 46, "stats": {"count": 23707132, "metrics": {"loss": 0.7752696638247888, "violators_lhs": 1.2251559151060534, "violators_rhs": 1.3979564883681417}}}
{"epoch_idx": 46, "edge_path_idx": 0, "edge_chunk_idx": 0, "lhs_partition": 0, "rhs_partition": 0, "index": 47, "stats": {"count": 23707132, "metrics": {"loss": 0.7739846193549613, "violators_lhs": 1.222648104376354, "violators_rhs": 1.3963818989154826}}}
{"epoch_idx": 47, "edge_path_idx": 0, "edge_chunk_idx": 0, "lhs_partition": 0, "rhs_partition": 0, "index": 48, "stats": {"count": 23707132, "metrics": {"loss": 0.772619100184912, "violators_lhs": 1.2197043488853903, "violators_rhs": 1.3950147997657414}}}
{"epoch_idx": 48, "edge_path_idx": 0, "edge_chunk_idx": 0, "lhs_partition": 0, "rhs_partition": 0, "index": 49, "stats": {"count": 23707132, "metrics": {"loss": 0.7713260522850279, "violators_lhs": 1.2170054985984808, "violators_rhs": 1.3935449467274237}}}
{"epoch_idx": 49, "edge_path_idx": 0, "edge_chunk_idx": 0, "lhs_partition": 0, "rhs_partition": 0, "index": 50, "stats": {"count": 23707132, "metrics": {"loss": 0.7704016795760019, "violators_lhs": 1.2145851299094297, "violators_rhs": 1.3929196496649194}}}
{"epoch_idx": 50, "edge_path_idx": 0, "edge_chunk_idx": 0, "lhs_partition": 0, "rhs_partition": 0, "index": 51, "stats": {"count": 23707132, "metrics": {"loss": 0.7691888272978792, "violators_lhs": 1.2126133182200192, "violators_rhs": 1.3916476273890912}}}
{"epoch_idx": 51, "edge_path_idx": 0, "edge_chunk_idx": 0, "lhs_partition": 0, "rhs_partition": 0, "index": 52, "stats": {"count": 23707132, "metrics": {"loss": 0.7680744044215416, "violators_lhs": 1.2104826935624267, "violators_rhs": 1.3904558341346394}}}
